{
    "mon": {
        "ch": {
            "0": [
                "УП.02.01 Составление картографических материалов с применением ГИС",
                "Шумилова Т.А., Трубин А.В.",
                "Б407, А401"
            ],
            "1": [
                "УП.02.01 Составление картографических материалов с применением ГИС",
                "Шумилова Т.А., Трубин А.В.",
                "Б407, А401"
            ],
            "2": [
                "МДК.04.01.Градостроительство",
                "Шумилова Т.А.",
                "А401"
            ],
            "3": [
                "МДК.04.01.Градостроительство",
                "Шумилова Т.А.",
                "А403"
            ]
        },
        "zn": {}
    },
    "tue": {
        "ch": {
            "2": [
                "МДК.02.01.Составление картографических материалов и ведение кадастров с использованием ИТ",
                "Шумилова Т.А., Федорова А.А.",
                "ДОТ"
            ],
            "3": [
                "МДК.02.01.Составление картографических материалов и ведение кадастров с использованием ИТ",
                "Шумилова Т.А.",
                "ДОТ"
            ],
            "4": [
                "МДК.04.01.Градостроительство",
                "Шумилова Т.А.",
                "ДОТ"
            ]
        },
        "zn": {
            "3": [
                "МДК.02.01.Составление картографических материалов и ведение кадастров с использованием ИТ",
                "Шумилова Т.А., Федорова А.А.",
                "ДОТ"
            ]
        }
    },
    "wed": {
        "ch": {
            "0": [
                "МДК.02.02.Математическая обработка результатов геодезических измерений п/гр2",
                "Рангелова Н.М.",
                "А401"
            ],
            "1": [
                "Иностранный язык",
                "Ткаченко Г.А., Темофеева Е.Н.",
                "А412, А415"
            ],
            "2": [
                "МДК.03.01.Техническая оценка и инвентаризация обьектов недвижимости п/гр1",
                "Рангелова Н.М.",
                "А401"
            ]
        },
        "zn": {
            "0": [
                "МДК.02.02.Математическая обработка результатов геодезических измерений п/гр1",
                "Рангелова Н.М.",
                "А401"
            ],
            "2": [
                "МДК.03.01.Техническая оценка и инвентаризация обьектов недвижимости п/гр2",
                "Рангелова Н.М.",
                "А401"
            ]
        }
    },
    "thu": {
        "ch": {
            "1": [
                "МДК.02.01.Составление картографических материалов и ведение кадастров с использованием ИТ",
                "Шумилова Т.А.",
                "А401"
            ],
            "2": [
                "МДК.02.01.Составление картографических материалов и ведение кадастров с использованием ИТ",
                "Шумилова Т.А., Федорова А.А.",
                "Б407, А401"
            ],
            "3": [
                "МДК.02.01.Составление картографических материалов и ведение кадастров с использованием ИТ",
                "Шумилова Т.А., Федорова А.А.",
                "Б407, А401"
            ],
            "4": [
                "МДК.05.01.Выполнение топографо-геодезических измерений",
                "Федорова А.А., Сивачева М.С.",
                "А401, А403"
            ]
        },
        "zn": {
            "1": [
                "МДК.02.01.Составление картографических материалов и ведение кадастров с использованием ИТ",
                "Шумилова Т.А., Федорова А.А.",
                "Б407, А401"
            ]
        }
    },
    "fri": {
        "ch": {
            "1": [
                "МДК.02.02.Математическая обработка результатов геодезических измерений",
                "Рангелова Н.М.",
                "А401"
            ],
            "2": [
                "МДК.03.01.Техническая оценка и инвентаризация объектов недвижимости",
                "Рангелова Н.М.",
                "А401"
            ],
            "3": [
                "МДК.03.01.Техническая оценка и инвентаризация объектов недвижимости п/гр1",
                "Рангелова Н.М.",
                "А401"
            ]
        },
        "zn": {
            "1": [
                "МДК.05.01.Выполнение топографо-геодезических измерений",
                "Федорова А.А.",
                "А401"
            ],
            "3": [
                "МДК.03.01.Техническая оценка и инвентаризация объектов недвижимости п/гр2",
                "Рангелова Н.М.",
                "А401"
            ]
        }
    },
    "sat": {
        "ch": {
            "0": [
                "Основы философии",
                "Смирнов Б.Е.",
                "А201"
            ],
            "1": [
                "Физическая культура",
                "Дворниченко Г.В.",
                "Спорт.пл"
            ],
            "2": [
                "Эффективное поведение на рынке труда ",
                "Попов В.А",
                "А410"
            ]
        },
        "zn": {}
    }
}